odoo/addons/hr_employee_ppe/README.rst
odoo/addons/hr_employee_ppe/__init__.py
odoo/addons/hr_employee_ppe/__manifest__.py
odoo/addons/hr_employee_ppe/data/hr_employee_ppe_cron.xml
odoo/addons/hr_employee_ppe/demo/hr_employee_ppe_demo.xml
odoo/addons/hr_employee_ppe/i18n/hr_employee_ppe.pot
odoo/addons/hr_employee_ppe/i18n/it.po
odoo/addons/hr_employee_ppe/i18n/pt_BR.po
odoo/addons/hr_employee_ppe/models/__init__.py
odoo/addons/hr_employee_ppe/models/hr_employee.py
odoo/addons/hr_employee_ppe/models/hr_employee_ppe.py
odoo/addons/hr_employee_ppe/models/hr_employee_ppe_equipment.py
odoo/addons/hr_employee_ppe/readme/CONFIGURE.rst
odoo/addons/hr_employee_ppe/readme/CONTRIBUTORS.rst
odoo/addons/hr_employee_ppe/readme/CREDITS.rst
odoo/addons/hr_employee_ppe/readme/DESCRIPTION.rst
odoo/addons/hr_employee_ppe/readme/INSTALL.rst
odoo/addons/hr_employee_ppe/readme/USAGE.rst
odoo/addons/hr_employee_ppe/security/hr_employee_ppe_equipment.xml
odoo/addons/hr_employee_ppe/security/hr_security.xml
odoo/addons/hr_employee_ppe/security/ir.model.access.csv
odoo/addons/hr_employee_ppe/static/description/banner.png
odoo/addons/hr_employee_ppe/static/description/icon.png
odoo/addons/hr_employee_ppe/static/description/index.html
odoo/addons/hr_employee_ppe/tests/__init__.py
odoo/addons/hr_employee_ppe/tests/test_hr_employee_ppe.py
odoo/addons/hr_employee_ppe/views/hr_employee_ppe_equipment.xml
odoo/addons/hr_employee_ppe/views/hr_employee_ppe_view.xml
odoo/addons/hr_employee_ppe/views/hr_employee_view.xml
odoo12_addon_hr_employee_ppe-12.0.1.1.1.dist-info/METADATA
odoo12_addon_hr_employee_ppe-12.0.1.1.1.dist-info/WHEEL
odoo12_addon_hr_employee_ppe-12.0.1.1.1.dist-info/top_level.txt
odoo12_addon_hr_employee_ppe-12.0.1.1.1.dist-info/RECORD
